<?xml version="1.0" encoding="utf-8" ?>
<dwsync>
<file name="db_connect.php" server="C:/xampp/htdocs/espbt/" local="130932549427350293" remote="130932549420000000" />
<file name="login-box.css" server="C:/xampp/htdocs/espbt/" local="130233443980000000" remote="130233443980000000" />
<file name="generic.css" server="C:/xampp/htdocs/espbt/" local="130233443980000000" remote="130233443980000000" />
<file name="page_layout.css" server="C:/xampp/htdocs/espbt/" local="130924058658085609" remote="130924058650000000" />
<file name="styles.css" server="C:/xampp/htdocs/espbt/" local="130937986438903902" remote="130937986430000000" />
<file name="script.js" server="C:/xampp/htdocs/espbt/" local="130495660260000000" remote="130495660260000000" />
<file name="login_process.php" server="C:/xampp/htdocs/espbt/" local="130233442960000000" remote="130233442960000000" />
<file name="head_common.php" server="C:/xampp/htdocs/espbt/" local="130233911820000000" remote="130233911820000000" />
<file name="banner_menu.php" server="C:/xampp/htdocs/espbt/" local="130942842794144387" remote="130942842790000000" />
<file name="login.php" server="C:/xampp/htdocs/espbt/" local="130937183279302005" remote="130937183270000000" />
<file name="index.php" server="C:/xampp/htdocs/espbt/" local="130944053699892190" remote="130944053690000000" />
</dwsync>